{
  "ngDeps": {
    "1": "angular2.src.core.metadata.di",
    "3": [
      {
        "1": "package:angular2/src/core/facade/lang.dart",
        "2": [
          "Type",
          "stringify",
          "isPresent",
          "StringWrapper",
          "isString"
        ],
        "5": false
      },
      {
        "1": "package:angular2/src/core/di.dart",
        "2": [
          "resolveForwardRef"
        ],
        "5": false
      },
      {
        "1": "package:angular2/src/core/di.ng_deps.dart",
        "4": "i1",
        "6": true
      },
      {
        "1": "package:angular2/src/core/di/metadata.dart",
        "2": [
          "DependencyMetadata"
        ],
        "5": false
      },
      {
        "1": "package:angular2/src/core/di/metadata.ng_deps.dart",
        "4": "i2",
        "6": true
      }
    ],
    "6": "di.dart"
  }
}